keras_image_helper/__init__.py
keras_image_helper/__version__.py
keras_image_helper/base.py
keras_image_helper/helper.py
keras_image_helper/preprocessors.py
keras_image_helper-0.0.2.dist-info/METADATA
keras_image_helper-0.0.2.dist-info/WHEEL
keras_image_helper-0.0.2.dist-info/licenses/LICENCE
keras_image_helper-0.0.2.dist-info/RECORD
