Metadata-Version: 2.4
Name: keras-image-helper
Version: 0.0.2
Summary: A lightweight library for pre-processing images for pre-trained keras models
Project-URL: Homepage, https://github.com/alexeygrigorev/keras-image-helper
Project-URL: Repository, https://github.com/alexeygrigorev/keras-image-helper
Project-URL: Issues, https://github.com/alexeygrigorev/keras-image-helper/issues
Author-email: Alexey Grigorev <alexey@datatalks.club>
Maintainer-email: Alexey Grigorev <alexey@datatalks.club>
License-File: LICENCE
Classifier: Development Status :: 4 - Beta
Classifier: Intended Audience :: Developers
Classifier: License :: Other/Proprietary License
Classifier: Programming Language :: Python :: 3
Classifier: Programming Language :: Python :: 3.11
Classifier: Programming Language :: Python :: 3.12
Classifier: Programming Language :: Python :: 3.13
Classifier: Topic :: Software Development :: Libraries :: Python Modules
Requires-Python: >=3.11
Requires-Dist: numpy>=2.3.2
Requires-Dist: pillow>=11.3.0
